riskfolio_lib-7.0.1.dist-info/top_level.txt
riskfolio_lib-7.0.1.dist-info/RECORD
riskfolio_lib-7.0.1.dist-info/METADATA
riskfolio_lib-7.0.1.dist-info/WHEEL
riskfolio_lib-7.0.1.dist-info/licenses/LICENSE.txt
riskfolio/version.py
riskfolio/__init__.py
riskfolio/external/__init__.py
riskfolio/external/cppfunctions.py
riskfolio/external/functions.cpython-39-x86_64-linux-gnu.so
riskfolio/src/AuxFunctions.py
riskfolio/src/DBHT.py
riskfolio/src/GerberStatistic.py
riskfolio/src/ParamsEstimation.py
riskfolio/src/OwaWeights.py
riskfolio/src/Reports.py
riskfolio/src/__init__.py
riskfolio/src/HCPortfolio.py
riskfolio/src/RiskFunctions.py
riskfolio/src/ConstraintsFunctions.py
riskfolio/src/PlotFunctions.py
riskfolio/src/Portfolio.py
