Metadata-Version: 2.4
Name: Riskfolio-Lib
Version: 7.0.1
Summary: Portfolio Optimization and Quantitative Strategic Asset Allocation in Python
Home-page: https://github.com/dcajasn/Riskfolio-Lib
Download-URL: https://github.com/dcajasn/Riskfolio-Lib.git
Author: Dany Cajas
Author-email: dany.cajas.n@uni.pe
Maintainer: Dany Cajas
Maintainer-email: dany.cajas.n@uni.pe
License: BSD (3-clause)
Project-URL: Documentation, https://riskfolio-lib.readthedocs.io/en/latest/
Project-URL: Issues, https://github.com/dcajasn/Riskfolio-Lib/issues
Project-URL: Personal website, http://financioneroncios.wordpress.com
Keywords: finance,portfolio,optimization,quant,asset,allocation,investing
Classifier: Intended Audience :: Financial and Insurance Industry
Classifier: Intended Audience :: Science/Research
Classifier: Programming Language :: Python :: 3.9
Classifier: Programming Language :: Python :: 3.10
Classifier: Programming Language :: Python :: 3.11
Classifier: Programming Language :: Python :: 3.12
Classifier: License :: OSI Approved :: BSD License
Classifier: Topic :: Office/Business :: Financial :: Investment
Classifier: Topic :: Office/Business :: Financial
Classifier: Topic :: Scientific/Engineering :: Mathematics
Classifier: Operating System :: Microsoft
Classifier: Operating System :: Unix
Classifier: Operating System :: MacOS
Requires-Python: >=3.9
License-File: LICENSE.txt
Requires-Dist: numpy>=1.24.0
Requires-Dist: scipy>=1.10.0
Requires-Dist: pandas>=2.0.0
Requires-Dist: matplotlib>=3.8.0
Requires-Dist: clarabel>=0.6.0
Requires-Dist: cvxpy>=1.5.2
Requires-Dist: scikit-learn>=1.3.0
Requires-Dist: statsmodels>=0.13.5
Requires-Dist: arch>=7.0
Requires-Dist: xlsxwriter>=3.1.2
Requires-Dist: networkx>=3.0
Requires-Dist: astropy>=5.1
Requires-Dist: pybind11>=2.10.1
Dynamic: author
Dynamic: author-email
Dynamic: classifier
Dynamic: description
Dynamic: description-content-type
Dynamic: download-url
Dynamic: home-page
Dynamic: keywords
Dynamic: license
Dynamic: license-file
Dynamic: maintainer
Dynamic: maintainer-email
Dynamic: project-url
Dynamic: requires-dist
Dynamic: requires-python
Dynamic: summary
